wav2aug/cpu/__init__.py
wav2aug/cpu/_amplitude_clipping.py
wav2aug/cpu/_amplitude_scaling.py
wav2aug/cpu/_aug_utils.py
wav2aug/cpu/_babble_noise_addition.py
wav2aug/cpu/_chunk_swapping.py
wav2aug/cpu/_frequency_dropout.py
wav2aug/cpu/_noise_addition.py
wav2aug/cpu/_polarity_inversion.py
wav2aug/cpu/_speed_perturbation.py
wav2aug/cpu/_time_dropout.py
wav2aug/cpu/wav2aug.py
wav2aug/data/fetch.py
wav2aug/data/packs.py
wav2aug/data/utils.py
wav2aug-0.1.0.dist-info/licenses/LICENSE
wav2aug-0.1.0.dist-info/METADATA
wav2aug-0.1.0.dist-info/WHEEL
wav2aug-0.1.0.dist-info/top_level.txt
wav2aug-0.1.0.dist-info/RECORD
