Metadata-Version: 2.4
Name: wav2aug
Version: 0.1.0
Summary: A general speech augmentation policy
Author: gfdb
License: Apache-2.0
Project-URL: Homepage, https://github.com/gfdb/wav2aug
Project-URL: Repository, https://github.com/gfdb/wav2aug
Project-URL: Issues, https://github.com/gfdb/wav2aug/issues
Project-URL: Documentation, https://github.com/gfdb/wav2aug#readme
Keywords: audio,speech,augmentation,pytorch,machine-learning,deep-learning
Classifier: Development Status :: 3 - Alpha
Classifier: Intended Audience :: Developers
Classifier: Intended Audience :: Science/Research
Classifier: License :: OSI Approved :: Apache Software License
Classifier: Programming Language :: Python :: 3
Classifier: Programming Language :: Python :: 3.10
Classifier: Programming Language :: Python :: 3.11
Classifier: Programming Language :: Python :: 3.12
Classifier: Topic :: Scientific/Engineering :: Artificial Intelligence
Classifier: Topic :: Multimedia :: Sound/Audio :: Analysis
Classifier: Topic :: Software Development :: Libraries :: Python Modules
Requires-Python: >=3.10
License-File: LICENSE
Requires-Dist: torch>=2.8.0
Requires-Dist: torchcodec>=0.7.0
Provides-Extra: test
Requires-Dist: pytest>=8; extra == "test"
Requires-Dist: pytest-cov; extra == "test"
Dynamic: license-file
